scd/__init__.py
scd/configs.json
scd/train.py
scd/config/__init__.py
scd/config/structures.py
scd/models/__init__.py
scd/models/scd.py
scd/models/timestamping.py
scd/processing/__init__.py
scd/processing/postprocess.py
scd/processing/preprocess.py
scd/utils/__init__.py
scd/utils/plotting.py
swarm_contrastive_decomposition-0.1.0.dist-info/licenses/LICENSE
swarm_contrastive_decomposition-0.1.0.dist-info/METADATA
swarm_contrastive_decomposition-0.1.0.dist-info/WHEEL
swarm_contrastive_decomposition-0.1.0.dist-info/top_level.txt
swarm_contrastive_decomposition-0.1.0.dist-info/RECORD
