Metadata-Version: 2.4
Name: swarm-contrastive-decomposition
Version: 0.1.0
Summary: Decomposition of Neurophysiological Time Series Signals with a Particle Swarm Optimised Independence Estimator
Author-email: Agnese Grison <agnese.grison16@imperial.ac.uk>
License: CC-BY-NC-4.0
Project-URL: Homepage, https://github.com/AgneGris/swarm-contrastive-decomposition
Project-URL: Repository, https://github.com/AgneGris/swarm-contrastive-decomposition
Project-URL: Issues, https://github.com/AgneGris/swarm-contrastive-decomposition/issues
Keywords: EMG,neural signals,decomposition,particle swarm,ICA,blind source separation
Classifier: Development Status :: 4 - Beta
Classifier: Intended Audience :: Science/Research
Classifier: Programming Language :: Python :: 3
Classifier: Programming Language :: Python :: 3.10
Classifier: Programming Language :: Python :: 3.11
Classifier: Topic :: Scientific/Engineering :: Bio-Informatics
Requires-Python: >=3.10
License-File: LICENSE
Requires-Dist: numpy>=1.20.0
Requires-Dist: torch>=1.9.0
Requires-Dist: scipy>=1.7.0
Requires-Dist: h5py>=3.0.0
Requires-Dist: mat73>=0.59
Requires-Dist: matplotlib>=3.5.0
Provides-Extra: dev
Requires-Dist: pytest>=7.0; extra == "dev"
Requires-Dist: black>=23.0; extra == "dev"
Dynamic: license-file
